{
"m(ARM)_pos":
{
    "type": "sensor",
    "name": "M(SAME[ARM]) Arm In-position Detector",
    "name_alt": "M(SAME[ARM]) Folding Sensor",
    "name_spanish": "Sensor de Plegado del Brazo M(SAME[ARM])",
    "material_num": "BC.AG.SS000547",
    "material_name": "Aircraft Arm In-position Detector Signal Cable"
},
"esc_(MOTOR)":
{
    "type": "esc",
    "name": "ESC (SAME[MOTOR])",
    "name_spanish": "ESC (SAME[MOTOR])",
    "material_num": "BC.AG.SS000563",
    "material_name": "ESC Module"
},
"motor_(MOTOR)":
{
    "type": "motor",
    "name": "Motor (SAME[MOTOR])",
    "name_spanish": "Motor (SAME[MOTOR])",
    "material_num": "BC.AG.SS000668",
    "material_name": "Propulsion Motor 10033"
}
}
